fbh/__init__.py
fbh/cli.py
fbh/core.py
team_x_og/__init__.py
team_x_og/bot.py
team_x_og/cli.py
team_x_og/errors.py
team_x_og/handlers.py
team_x_og/inline.py
team_x_og/keyboard.py
team_x_og/media.py
team_x_og/plugins.py
fbh-0.1.0.dist-info/LICENSE
fbh-0.1.0.dist-info/METADATA
fbh-0.1.0.dist-info/WHEEL
fbh-0.1.0.dist-info/entry_points.txt
fbh-0.1.0.dist-info/top_level.txt
fbh-0.1.0.dist-info/RECORD
