Metadata-Version: 2.1
Name: fbh
Version: 0.1.0
Summary: File encryption/decryption tool
Home-page: https://t.me/TEAM_X_OG
Author: Mr arman
Author-email: armanhacker95@gmail.com
License-File: LICENSE
Requires-Dist: pycryptodome
